[
  {
    "id": "65ab6120ab0f963440ec09af",
    "image" : "",
    "name": "Gomez Jennings",
    "stock" : 150,
    "quantity" : 1
  },
  {
    "id": "65ab61201631fcf1d59336f8",
    "image" : "https://images.unsplash.com/photo-1612144431180-2d672779556c?q=80&w=1000&auto=format&fit=crop&ixlib=rb-4.0.3&ixid=M3wxMjA3fDB8MHxzZWFyY2h8N3x8c21hbGx8ZW58MHx8MHx8fDA%3D",
    "name": "Stokes Mcneil",
    "stock" : 120,
    "quantity" : 1
  },
  {
    "id": "65ab6120a955af4c563bf912",
    "image" : "https://images.unsplash.com/photo-1612144431180-2d672779556c?q=80&w=1000&auto=format&fit=crop&ixlib=rb-4.0.3&ixid=M3wxMjA3fDB8MHxzZWFyY2h8N3x8c21hbGx8ZW58MHx8MHx8fDA%3D",
    "name": "Loraine Patel",
    "stock" : 0,
    "quantity" : 1
  },
  {
    "id": "65ab612072a04a568f105d56",
    "image" : "https://images.unsplash.com/photo-1612144431180-2d672779556c?q=80&w=1000&auto=format&fit=crop&ixlib=rb-4.0.3&ixid=M3wxMjA3fDB8MHxzZWFyY2h8N3x8c21hbGx8ZW58MHx8MHx8fDA%3D",
    "name": "Mccoy Coleman",
    "stock" : 150,
    "quantity" : 1
  },
  {
    "id": "65ab612043b52f5857af2b70",
    "image" : "https://images.unsplash.com/photo-1612144431180-2d672779556c?q=80&w=1000&auto=format&fit=crop&ixlib=rb-4.0.3&ixid=M3wxMjA3fDB8MHxzZWFyY2h8N3x8c21hbGx8ZW58MHx8MHx8fDA%3D",
    "name": "Conner Mcfadden",
    "stock" : 15,
    "quantity" : 1
  },
  {
    "id": "65ab61205f9d90e17553f967",
    "image" : "https://images.unsplash.com/photo-1612144431180-2d672779556c?q=80&w=1000&auto=format&fit=crop&ixlib=rb-4.0.3&ixid=M3wxMjA3fDB8MHxzZWFyY2h8N3x8c21hbGx8ZW58MHx8MHx8fDA%3D",
    "name": "Sheryl Cooley",
    "stock" : 150,
    "quantity" : 1
  },
  {
    "id": "65ab61205ff436ff9069d81e",
    "image" : "https://images.unsplash.com/photo-1612144431180-2d672779556c?q=80&w=1000&auto=format&fit=crop&ixlib=rb-4.0.3&ixid=M3wxMjA3fDB8MHxzZWFyY2h8N3x8c21hbGx8ZW58MHx8MHx8fDA%3D",
    "name": "Doyle Dixon",
    "stock" : 150,
    "quantity" : 1
  },
  {
    "id": "65ab6120901881d983371da9",
    "image" : "",
    "name": "Cline Cohen",
    "stock" : 150,
    "quantity" : 1
  },
  {
    "id": "65ab612057ea7c452d110e2a",
    "image" : "https://images.unsplash.com/photo-1612144431180-2d672779556c?q=80&w=1000&auto=format&fit=crop&ixlib=rb-4.0.3&ixid=M3wxMjA3fDB8MHxzZWFyY2h8N3x8c21hbGx8ZW58MHx8MHx8fDA%3D",
    "name": "Donovan Schneider",
    "stock" : 150,
    "quantity" : 1
  },
  {
    "id": "65ab612038624100347c8155",
    "image" : "https://images.unsplash.com/photo-1612144431180-2d672779556c?q=80&w=1000&auto=format&fit=crop&ixlib=rb-4.0.3&ixid=M3wxMjA3fDB8MHxzZWFyY2h8N3x8c21hbGx8ZW58MHx8MHx8fDA%3D",
    "name": "Darcy Sullivan",
    "stock" : 150,
    "quantity" : 1
  },
  {
    "id": "65ab6120df3f02dd776cb3a1",
    "image" : "https://images.unsplash.com/photo-1612144431180-2d672779556c?q=80&w=1000&auto=format&fit=crop&ixlib=rb-4.0.3&ixid=M3wxMjA3fDB8MHxzZWFyY2h8N3x8c21hbGx8ZW58MHx8MHx8fDA%3D",
    "name": "Theresa Pope",
    "stock" : 150,
    "quantity" : 1
  },
  {
    "id": "65ab61205fb7b3a6215819eb",
    "image" : "https://images.unsplash.com/photo-1612144431180-2d672779556c?q=80&w=1000&auto=format&fit=crop&ixlib=rb-4.0.3&ixid=M3wxMjA3fDB8MHxzZWFyY2h8N3x8c21hbGx8ZW58MHx8MHx8fDA%3D",
    "name": "Parks Velazquez",
    "stock" : 150,
    "quantity" : 1
  },
  {
    "id": "65ab6120449fbb3b8cead81f",
    "image" : "https://images.unsplash.com/photo-1612144431180-2d672779556c?q=80&w=1000&auto=format&fit=crop&ixlib=rb-4.0.3&ixid=M3wxMjA3fDB8MHxzZWFyY2h8N3x8c21hbGx8ZW58MHx8MHx8fDA%3D",
    "name": "George Pierce",
    "stock" : 150,
    "quantity" : 1
  },
  {
    "id": "65ab6120eea01c067882657c",
    "image" : "https://images.unsplash.com/photo-1612144431180-2d672779556c?q=80&w=1000&auto=format&fit=crop&ixlib=rb-4.0.3&ixid=M3wxMjA3fDB8MHxzZWFyY2h8N3x8c21hbGx8ZW58MHx8MHx8fDA%3D",
    "name": "Walsh Lynn",
    "stock" : 150,
    "quantity" : 1
  },
  {
    "id": "65ab6120146d872727fa5eba",
    "image" : "https://images.unsplash.com/photo-1612144431180-2d672779556c?q=80&w=1000&auto=format&fit=crop&ixlib=rb-4.0.3&ixid=M3wxMjA3fDB8MHxzZWFyY2h8N3x8c21hbGx8ZW58MHx8MHx8fDA%3D",
    "name": "Ferguson Callahan",
    "stock" : 150,
    "quantity" : 1
  }
]